pyvider/__init__.py
pyvider/cty/__init__.py
pyvider/cty/codec.py
pyvider/cty/marks.py
pyvider/cty/parser.py
pyvider/cty/py.typed
pyvider/cty/config/__init__.py
pyvider/cty/config/defaults.py
pyvider/cty/config/runtime.py
pyvider/cty/context/__init__.py
pyvider/cty/context/validation_context.py
pyvider/cty/conversion/__init__.py
pyvider/cty/conversion/_utils.py
pyvider/cty/conversion/adapter.py
pyvider/cty/conversion/explicit.py
pyvider/cty/conversion/inference_cache.py
pyvider/cty/conversion/raw_to_cty.py
pyvider/cty/conversion/type_encoder.py
pyvider/cty/exceptions/__init__.py
pyvider/cty/exceptions/base.py
pyvider/cty/exceptions/conversion.py
pyvider/cty/exceptions/encoding.py
pyvider/cty/exceptions/validation.py
pyvider/cty/functions/__init__.py
pyvider/cty/functions/bytes_functions.py
pyvider/cty/functions/collection_functions.py
pyvider/cty/functions/comparison_functions.py
pyvider/cty/functions/conversion_functions.py
pyvider/cty/functions/datetime_functions.py
pyvider/cty/functions/encoding_functions.py
pyvider/cty/functions/numeric_functions.py
pyvider/cty/functions/string_functions.py
pyvider/cty/functions/structural_functions.py
pyvider/cty/path/__init__.py
pyvider/cty/path/base.py
pyvider/cty/types/__init__.py
pyvider/cty/types/base.py
pyvider/cty/types/capsule.py
pyvider/cty/types/capsule_types.py
pyvider/cty/types/collections/__init__.py
pyvider/cty/types/collections/list.py
pyvider/cty/types/collections/map.py
pyvider/cty/types/collections/set.py
pyvider/cty/types/primitives/__init__.py
pyvider/cty/types/primitives/bool.py
pyvider/cty/types/primitives/number.py
pyvider/cty/types/primitives/string.py
pyvider/cty/types/structural/__init__.py
pyvider/cty/types/structural/dynamic.py
pyvider/cty/types/structural/object.py
pyvider/cty/types/structural/tuple.py
pyvider/cty/utils/__init__.py
pyvider/cty/utils/strings.py
pyvider/cty/validation/__init__.py
pyvider/cty/validation/recursion.py
pyvider/cty/values/__init__.py
pyvider/cty/values/base.py
pyvider_cty-0.0.1111.dist-info/licenses/LICENSE
pyvider_cty-0.0.1111.dist-info/METADATA
pyvider_cty-0.0.1111.dist-info/WHEEL
pyvider_cty-0.0.1111.dist-info/top_level.txt
pyvider_cty-0.0.1111.dist-info/RECORD
