Metadata-Version: 2.4
Name: pyvider-cty
Version: 0.0.1111
Summary: Pure-Python implementation of the go-cty type system with strong validation, serialization, and Terraform interoperability
Author-email: Tim Perkins <code@tim.life>
Maintainer-email: "provide.io" <code@provide.io>
License-Expression: Apache-2.0
Classifier: Development Status :: 3 - Alpha
Classifier: Intended Audience :: Developers
Classifier: Operating System :: OS Independent
Classifier: Programming Language :: Python :: 3
Classifier: Programming Language :: Python :: 3.11
Classifier: Programming Language :: Python :: 3.12
Classifier: Programming Language :: Python :: 3.13
Classifier: Programming Language :: Python :: 3.14
Classifier: Typing :: Typed
Requires-Python: >=3.11
License-File: LICENSE
Requires-Dist: attrs>=25.1.0
Requires-Dist: msgpack>=1.1.0
Requires-Dist: provide-foundation
Dynamic: license-file
